pydiagrams/AWS.py
pydiagrams/Architecture.py
pydiagrams/ArchitectureDiagrams.py
pydiagrams/Component.py
pydiagrams/Diagram.py
pydiagrams/Flowchart.py
pydiagrams/Model.py
pydiagrams/Views.py
pydiagrams/__init__.py
pydiagrams/baseItems.py
pydiagrams/__pycache__/Component.cpython-38.pyc
pydiagrams/__pycache__/Diagram.cpython-38.pyc
pydiagrams/__pycache__/__init__.cpython-38.pyc
pydiagrams/__pycache__/baseItems.cpython-38.pyc
pydiagrams/demos/AWS-FB_Loyalty.py
pydiagrams/demos/AWS-Simple_Example.py
pydiagrams/demos/AWS-demo.py
pydiagrams/demos/Architecture-demo-Ecomm.py
pydiagrams/demos/Component-demo-Bazaarvoice-v2.py
pydiagrams/demos/Component-demo-Bazaarvoice.py
pydiagrams/demos/Component-demo-DaaS-combined-v2.py
pydiagrams/demos/Component-demo-apps.py
pydiagrams/demos/Component-demo-together-advanced.py
pydiagrams/demos/Component-demo-together.py
pydiagrams/demos/Component-demo.py
pydiagrams/demos/Flowchart-demo-basic.diag.py
pydiagrams/demos/Flowchart-demo-example.py
pydiagrams/demos/Flowchart-demo-shapes.py
pydiagrams/demos/Flowchart-demo.py
pydiagrams/demos/Flowchart-new-demo.py
pydiagrams/demos/GST.py
pydiagrams/demos/Views-data_architecture.py
pydiagrams/demos/Views-demo-basic.py
pydiagrams/demos/Views-demo-clusters.py
pydiagrams/demos/Views-demo-colors-shapes.py
pydiagrams/demos/Views-demo-sources.py
pydiagrams/demos/Wallets.py
pydiagrams/demos/pydiagrams-AWS.py
pydiagrams/demos/deprecated/Component-demo-Bazaarvoice.py
pydiagrams/demos/deprecated/Component-demo-DaaS-combined.py
pydiagrams/helpers/Blockdiag.py
pydiagrams/helpers/GraphML.py
pydiagrams/helpers/Graphviz.py
pydiagrams/helpers/Graphviz_AWS.py
pydiagrams/helpers/PUML.py
pydiagrams/helpers/PUML_AWS.py
pydiagrams/helpers/__init__.py
pydiagrams/helpers/arcentry.py
pydiagrams/helpers/constants.py
pydiagrams/helpers/helper.py
pydiagrams/helpers/__pycache__/PUML.cpython-38.pyc
pydiagrams/helpers/__pycache__/__init__.cpython-38.pyc
pydiagrams/helpers/__pycache__/constants.cpython-38.pyc
pydiagrams.egg-info/PKG-INFO
pydiagrams.egg-info/SOURCES.txt
pydiagrams.egg-info/dependency_links.txt
pydiagrams.egg-info/not-zip-safe
pydiagrams.egg-info/top_level.txt
pydiagrams-0.7.4.dist-info/LICENSE
pydiagrams-0.7.4.dist-info/METADATA
pydiagrams-0.7.4.dist-info/WHEEL
pydiagrams-0.7.4.dist-info/top_level.txt
pydiagrams-0.7.4.dist-info/RECORD
