Metadata-Version: 2.1
Name: pydiagrams
Version: 0.7.4
Summary: Generate software diagrams using Python syntax
Home-page: https://github.com/billingtonm/pydiagrams
Author: Matthew Billington
Author-email: mbillington@gmail.com
License: MIT
Platform: UNKNOWN
Classifier: Development Status :: 3 - Alpha
Classifier: Programming Language :: Python :: 3.8
Classifier: License :: OSI Approved :: MIT License
Classifier: Operating System :: OS Independent
Classifier: Intended Audience :: Developers
Classifier: Environment :: Console
Classifier: Topic :: Software Development
Requires-Python: >=3.8
Requires-Dist: colour
Requires-Dist: pillow
Requires-Dist: plantuml
